./.gitignore
./PKG-INFO
./README.md
./pyproject.toml
./vision_agents/plugins/heygen/__init__.py
./vision_agents/plugins/heygen/heygen_avatar_publisher.py
./vision_agents/plugins/heygen/heygen_rtc_manager.py
./vision_agents/plugins/heygen/heygen_session.py
./vision_agents/plugins/heygen/heygen_types.py
./vision_agents/plugins/heygen/heygen_video_track.py
vision_agents/plugins/heygen/__init__.py
vision_agents/plugins/heygen/heygen_avatar_publisher.py
vision_agents/plugins/heygen/heygen_rtc_manager.py
vision_agents/plugins/heygen/heygen_session.py
vision_agents/plugins/heygen/heygen_types.py
vision_agents/plugins/heygen/heygen_video_track.py
vision_agents_plugins_heygen-0.2.10.dist-info/METADATA
vision_agents_plugins_heygen-0.2.10.dist-info/WHEEL
vision_agents_plugins_heygen-0.2.10.dist-info/RECORD
