Metadata-Version: 2.4
Name: vision-agents-plugins-heygen
Version: 0.2.10
Summary: HeyGen avatar plugin for Vision Agents
Project-URL: Documentation, https://visionagents.ai/
Project-URL: Website, https://visionagents.ai/
Project-URL: Source, https://github.com/GetStream/Vision-Agents
License-Expression: MIT
Keywords: AI,agents,avatars,heygen,voice agents
Requires-Python: >=3.10
Requires-Dist: aiohttp>=3.9.0
Requires-Dist: aiortc>=1.9.0
Requires-Dist: vision-agents
